quests/__init__.py
quests/descriptor.py
quests/entropy.py
quests/geometry.py
quests/matrix.py
quests/mcmc.py
quests/cli/__init__.py
quests/cli/active_learning.py
quests/cli/approx_dH.py
quests/cli/bandwidth.py
quests/cli/compress.py
quests/cli/compute_dH.py
quests/cli/entropy.py
quests/cli/entropy_sampler.py
quests/cli/learning_curve.py
quests/cli/load_file.py
quests/cli/log.py
quests/cli/make_descriptors.py
quests/cli/mcmc.py
quests/cli/overlap.py
quests/cli/quests.py
quests/compression/__init__.py
quests/compression/baseline.py
quests/compression/compress.py
quests/compression/fps.py
quests/compression/metrics.py
quests/compression/parallel.py
quests/gpu/__init__.py
quests/gpu/entropy.py
quests/gpu/matrix.py
quests/tools/__init__.py
quests/tools/environment.py
quests/tools/example.py
quests/tools/pbc.py
quests/tools/plotting.py
quests/tools/polyfit.py
quests/tools/time.py
quests-2025.9.29.dist-info/licenses/LICENSE
quests-2025.9.29.dist-info/licenses/NOTICE
quests-2025.9.29.dist-info/METADATA
quests-2025.9.29.dist-info/WHEEL
quests-2025.9.29.dist-info/entry_points.txt
quests-2025.9.29.dist-info/top_level.txt
quests-2025.9.29.dist-info/RECORD
