Metadata-Version: 2.4
Name: quests
Version: 2025.9.29
Summary: Quick Uncertainty and Entropy from STructural Similarity
Author-email: Daniel Schwalbe-Koda <dskoda@ucla.edu>
License: BSD 3-Clause License
Keywords: feed,reader,tutorial
Requires-Python: >=3.8
License-File: LICENSE
License-File: NOTICE
Requires-Dist: numpy
Requires-Dist: pandas
Requires-Dist: numba
Requires-Dist: ase
Requires-Dist: click
Requires-Dist: pynndescent
Requires-Dist: scikit-learn
Requires-Dist: bayesian-optimization
Provides-Extra: docs
Requires-Dist: sphinx; extra == "docs"
Provides-Extra: gpu
Requires-Dist: torch; extra == "gpu"
Requires-Dist: torchvision; extra == "gpu"
Dynamic: license-file
